Metadata-Version: 1.0
Name: cssmin
Version: 0.1.3
Summary: A Python port of the YUI CSS compression algorithm.
Home-page: http://github.com/zacharyvoase/cssmin
Author: Zachary Voase
Author-email: zacharyvoase@me.com
License: UNKNOWN
Platform: UNKNOWN
